COPYING
COPYING.lesser
NOTICE
README.md
pyproject.toml
ppyrogam.egg-info/PKG-INFO
ppyrogam.egg-info/SOURCES.txt
ppyrogam.egg-info/dependency_links.txt
ppyrogam.egg-info/requires.txt
ppyrogam.egg-info/top_level.txt
pyrogram/__init__.py
pyrogram/client.py
pyrogram/dispatcher.py
pyrogram/emoji.py
pyrogram/file_id.py
pyrogram/filters.py
pyrogram/mime_types.py
pyrogram/py.typed
pyrogram/sync.py
pyrogram/utils.py
pyrogram/connection/__init__.py
pyrogram/connection/connection.py
pyrogram/connection/transport/__init__.py
pyrogram/connection/transport/tcp/__init__.py
pyrogram/connection/transport/tcp/tcp.py
pyrogram/connection/transport/tcp/tcp_abridged.py
pyrogram/connection/transport/tcp/tcp_abridged_o.py
pyrogram/connection/transport/tcp/tcp_full.py
pyrogram/connection/transport/tcp/tcp_intermediate.py
pyrogram/connection/transport/tcp/tcp_intermediate_o.py
pyrogram/crypto/__init__.py
pyrogram/crypto/aes.py
pyrogram/crypto/mtproto.py
pyrogram/crypto/prime.py
pyrogram/crypto/rsa.py
pyrogram/enums/__init__.py
pyrogram/enums/auto_name.py
pyrogram/enums/chat_action.py
pyrogram/enums/chat_event_action.py
pyrogram/enums/chat_member_status.py
pyrogram/enums/chat_members_filter.py
pyrogram/enums/chat_type.py
pyrogram/enums/client_platform.py
pyrogram/enums/message_entity_type.py
pyrogram/enums/message_media_type.py
pyrogram/enums/message_origin_type.py
pyrogram/enums/message_service_type.py
pyrogram/enums/messages_filter.py
pyrogram/enums/next_code_type.py
pyrogram/enums/parse_mode.py
pyrogram/enums/poll_type.py
pyrogram/enums/profile_color.py
pyrogram/enums/reaction_type.py
pyrogram/enums/reply_color.py
pyrogram/enums/sent_code_type.py
pyrogram/enums/stories_privacy_rules.py
pyrogram/enums/story_privacy.py
pyrogram/enums/user_status.py
pyrogram/errors/__init__.py
pyrogram/errors/rpc_error.py
pyrogram/errors/exceptions/__init__.py
pyrogram/errors/exceptions/all.py
pyrogram/errors/exceptions/bad_request_400.py
pyrogram/errors/exceptions/flood_420.py
pyrogram/errors/exceptions/forbidden_403.py
pyrogram/errors/exceptions/internal_server_error_500.py
pyrogram/errors/exceptions/not_acceptable_406.py
