Metadata-Version: 2.4
Name: ppyrogam
Version: 1.0.0
Summary: Custom build of Pyrogram for private use
Author-email: Your Name <you@example.com>
Requires-Python: >=3.8
License-File: COPYING
License-File: COPYING.lesser
License-File: NOTICE
Requires-Dist: tgcrypto
Requires-Dist: requests
Dynamic: license-file
